pyCATHY/__init__.py
pyCATHY/cathy_tools.py
pyCATHY/cathy_utils.py
pyCATHY/meshtools.py
pyCATHY/petro.py
pyCATHY/sensitivity.py
pyCATHY/DA/__init__.py
pyCATHY/DA/cathy_DA.py
pyCATHY/DA/deprecated_run_DA.py
pyCATHY/DA/enkf.py
pyCATHY/DA/observations.py
pyCATHY/DA/perturbate.py
pyCATHY/DA/pf.py
pyCATHY/ERT/__init__.py
pyCATHY/ERT/petro_Archie.py
pyCATHY/ERT/simulate_ERT.py
pyCATHY/importers/__init__.py
pyCATHY/importers/cathy_inputs.py
pyCATHY/importers/cathy_outputs.py
pyCATHY/importers/cathy_plant.py
pyCATHY/importers/sensors_measures.py
pyCATHY/plotters/__init__.py
pyCATHY/plotters/cathy_plots.py
pyCATHY/tests/__init__.py
pyCATHY/tests/test_DA_ERT_Tensio_SWC.py
pyCATHY/tests/test_DA_Feddes_ERT.py
pyCATHY/tests/test_DA_Noble.py
pyCATHY/tests/test_hydro_surfsurbsurface.py
pyCATHY/tests/test_mapping.py
pycathy-0.1.1.dist-info/LICENSE
pycathy-0.1.1.dist-info/METADATA
pycathy-0.1.1.dist-info/WHEEL
pycathy-0.1.1.dist-info/top_level.txt
pycathy-0.1.1.dist-info/zip-safe
pycathy-0.1.1.dist-info/RECORD
